n_edit/__init__.py
n_edit/commands.py
n_edit/editor.py
n_edit/execution.py
n_edit/layout.py
n_edit/model.py
n_edit/serializable.py
n_edit-0.16.0.dist-info/WHEEL
n_edit-0.16.0.dist-info/METADATA
n_edit-0.16.0.dist-info/RECORD
